Metadata-Version: 1.0
Name: bibtt
Version: 1.0.0
Summary: this is my first test
Home-page: https://www.bilibili.com/
Author: xushibo
Author-email: 937207118@qq.com
License: UNKNOWN
Platform: UNKNOWN
